elkwork/__init__.py
elkwork/mlp.py
elkwork-0.5.dist-info/METADATA
elkwork-0.5.dist-info/WHEEL
elkwork-0.5.dist-info/top_level.txt
elkwork-0.5.dist-info/RECORD
