Metadata-Version: 2.4
Name: elkwork
Version: 0.5
Summary: My homebrewed MLP library. Visit leonid-elkin.github.io for more info
Home-page: https://github.com/Leonid-Elkin
Author: Leonid Elkin
Author-email: lnd.elkn@gmail.com
Classifier: Programming Language :: Python :: 3
Classifier: License :: OSI Approved :: MIT License
Classifier: Programming Language :: Python :: 3.8
Requires-Dist: numpy
Dynamic: author
Dynamic: author-email
Dynamic: classifier
Dynamic: description
Dynamic: description-content-type
Dynamic: home-page
Dynamic: requires-dist
Dynamic: summary
